karolinka/__init__.py
karolinka/main.py
karolinka-0.2.post2.dist-info/licenses/LICENSE.md
karolinka-0.2.post2.dist-info/METADATA
karolinka-0.2.post2.dist-info/WHEEL
karolinka-0.2.post2.dist-info/top_level.txt
karolinka-0.2.post2.dist-info/RECORD
