Metadata-Version: 2.4
Name: karolinka
Version: 0.2.post2
Summary: Implementacja harcerskiego szyfru - Karolinki
Author-email: "Rafał Kiepiela (TexturedPolak)" <rafal200725@gmail.com>
License-Expression: MIT
Project-URL: Documentation, https://github.com/TexturedPolak/karolinka/
Project-URL: Repository, https://github.com/TexturedPolak/karolinka/
Project-URL: Issues, https://github.com/TexturedPolak/karolinka/issues
Classifier: Programming Language :: Python :: 3
Classifier: Operating System :: OS Independent
Classifier: Development Status :: 4 - Beta
Classifier: Environment :: Console
Classifier: Intended Audience :: Education
Classifier: Natural Language :: Polish
Requires-Python: >=3.9
License-File: LICENSE.md
Dynamic: license-file
